Workbook

Sheet How to Use
B2: ISO/IEC 5230:2020 Question Mapping & Recommendation Workbook
B4: Prepared for: Open Source Compliance Maturity Assessment
B7: What this workbook does
B9: This workbook maps all 27 assessment questions to the 6 key concepts (clauses) of ISO/IEC 5230:2020, weights each question within its topic by how mandatory and central it is to that clause, and then generates a tailored recommendation for every question based on the maturity score or Yes/No answer entered for it. Nothing here is generic boilerplate - every recommendation is written against the specific control the question is testing.
B11: Sheet guide
B13: - Question Mapping: the core working sheet. Enter a score in column J for each question; columns K and L update automatically with the maturity band and a tailored recommendation.
B15: - Division Recommendations: one strategic narrative per topic (division) covering sequencing, dependencies and quick wins - use this for the executive-level conversation, not just the line-item detail.
B17: - Topic Summary: the weighting rollup showing each topic sums to 1.00, plus the topic-level concept description.
B19: - Recommendation Library: the backing data behind the auto-recommendation formulas. Edit text here if wording needs to change; the Question Mapping sheet will pick up edits automatically.
B21: - ISO 5230 Clause Reference: a paraphrased quick-reference to the standard's 13 core requirements, for context.
B23: How scoring and bands work
B25: Maturity Scale questions use the client's native 0-5 scale. Per the assessment brief, scores are grouped into three recommendation bands:
... B41: These recommendations are written as practical, general guidance to accelerate a client conversation - they are not a substitute for a qualified legal or compliance professional's review before being finalized in a client deliverable, particularly anywhere license-obligation interpretation or contractual risk is involved.

Sheet Question Mapping
A1: Question ID | B1: Topic / Key Concept | C1: Rank in Topic | D1: Question | E1: ISO 5230:2020 Clause | F1: Requirement Type | G1: Weight | H1: Rationale | I1: Question Type | J1: Client Score | K1: Maturity / Answer Band | L1: Recommendation
A2: Q01 | B2: 1. Program Foundation (Policy, Roles, Competence, Awareness) | C2: 1 | D2: Are open source compliance roles and responsibilities clearly defined, assigned, and documented for each individual whose work may impact performance? | E2: S3.1.2 Competence (VM 3.1.2.1) | F2: Mandatory (shall) | G2: 0.16 | H2: Directly matches the standard's first Competence verification material - a documented list of roles and responsibilities. Foundational: the other competence/awareness requirements depend on roles being defined first. | I2: Maturity Scale (0-5) | K2: =IF(J2="","",IF(J2=0,"Band 0",IF(J2<=2,"Band 1-2","Band 3-5"))) | L2: =IF(K2="","Enter a score in column J to see a tailored recommendation.",IFERROR(INDEX('Recommendation Library'!$C:$C,MATCH($A2&"|"&K2,'Recommendation Library'!$D:$D,0)),"Recommendation not found - check the Recommendation Library tab.")) -> Enter a score in column J to see a tailored recommendation.
A3: Q02 | B3: 1. Program Foundation (Policy, Roles, Competence, Awareness) | C3: 2 | D3: Are the competencies for each role defined and aligned with your compliance program? | E3: S3.1.2 Competence (VM 3.1.2.2) | F3: Mandatory (shall) | G3: 0.14 | H3: Matches the second Competence verification material - determining the necessary competence per role. Second step after roles are defined. | I3: Maturity Scale (0-5) | K3: =IF(J3="","",IF(J3=0,"Band 0",IF(J3<=2,"Band 1-2","Band 3-5"))) | L3: =IF(K3="","Enter a score in column J to see a tailored recommendation.",IFERROR(INDEX('Recommendation Library'!$C:$C,MATCH($A3&"|"&K3,'Recommendation Library'!$D:$D,0)),"Recommendation not found - check the Recommendation Library tab.")) -> Enter a score in column J to see a tailored recommendation.
A4: Q03 | B4: 1. Program Foundation (Policy, Roles, Competence, Awareness) | C4: 3 | D4: Is each program participant's capabilities and competencies documented? | E4: S3.1.2 Competence (VM 3.1.2.3) | F4: Mandatory (shall) | G4: 0.13 | H4: Matches the third Competence verification material - documented evidence of assessed competence. Completes the 3-part requirement: roles -> required competence -> assessed evidence. | I4: Maturity Scale (0-5) | K4: =IF(J4="","",IF(J4=0,"Band 0",IF(J4<=2,"Band 1-2","Band 3-5"))) | L4: =IF(K4="","Enter a score in column J to see a tailored recommendation.",IFERROR(INDEX('Recommendation Library'!$C:$C,MATCH($A4&"|"&K4,'Recommendation Library'!$D:$D,0)),"Recommendation not found - check the Recommendation Library tab.")) -> Enter a score in column J to see a tailored recommendation.
A5: Q04 | B5: 1. Program Foundation (Policy, Roles, Competence, Awareness) | C5: 4 | D5: Is there any official documentation or defined procedure for employees to follow regarding the company's open source policy? | E5: S3.1.1 Policy (VM 3.1.1.1) | F5: Mandatory (shall) | G5: 0.13 | H5: This is the base requirement of the entire standard - a written, internally communicated open source policy must exist. Nearly every other clause assumes this policy exists. | I5: Maturity Scale (0-5) | K5: =IF(J5="","",IF(J5=0,"Band 0",IF(J5<=2,"Band 1-2","Band 3-5"))) | L5: =IF(K5="","Enter a score in column J to see a tailored recommendation.",IFERROR(INDEX('Recommendation Library'!$C:$C,MATCH($A5&"|"&K5,'Recommendation Library'!$D:$D,0)),"Recommendation not found - check the Recommendation Library tab.")) -> Enter a score in column J to see a tailored recommendation.
A6: Q05 | B6: 1. Program Foundation (Policy, Roles, Competence, Awareness) | C6: 5 | D6: Is there a documented policy that explains the scope, limits, and distribution rules for open source software? | E6: S3.1.4 Program Scope + S3.1.1 Policy | F6: Mandatory (shall) | G6: 0.12 | H6: Combines the Program Scope requirement (a written statement of scope and limits) with policy content on distribution. Scope must be declared before conformance can even be assessed. | I6: Maturity Scale (0-5) | K6: =IF(J6="","",IF(J6=0,"Band 0",IF(J6<=2,"Band 1-2","Band 3-5"))) | L6: =IF(K6="","Enter a score in column J to see a tailored recommendation.",IFERROR(INDEX('Recommendation Library'!$C:$C,MATCH($A6&"|"&K6,'Recommendation Library'!$D:$D,0)),"Recommendation not found - check the Recommendation Library tab.")) -> Enter a score in column J to see a tailored recommendation.
A7: Q06 | B7: 1. Program Foundation (Policy, Roles, Competence, Awareness) | C7: 6 | D7: Is there a documented procedure for reviewing and recording open source license obligations, restrictions, and rights for components listed in the SBOM? | E7: S3.1.5 License Obligations (VM 3.1.5.1) | F7: Mandatory (shall) | G7: 0.11 | H7: Matches the License Obligations requirement - a process to review identified licenses for obligations, restrictions and rights. Feeds directly into the BOM and license-use-case clauses. | I7: Maturity Scale (0-5) | K7: =IF(J7="","",IF(J7=0,"Band 0",IF(J7<=2,"Band 1-2","Band 3-5"))) | L7: =IF(K7="","Enter a score in column J to see a tailored recommendation.",IFERROR(INDEX('Recommendation Library'!$C:$C,MATCH($A7&"|"&K7,'Recommendation Library'!$D:$D,0)),"Recommendation not found - check the Recommendation Library tab.")) -> Enter a score in column J to see a tailored recommendation.
A8: Q07 | B8: 1. Program Foundation (Policy, Roles, Competence, Awareness) | C8: 7 | D8: Is there a system in place for mandatory learning and training on open-source software license compliance? | E8: S3.1.3 Awareness (VM 3.1.3.1) | F8: Mandatory (shall) | G8: 0.1 | H8: Matches the Awareness requirement - participants must be aware of the policy, objectives, their role, and the consequences of non-conformance, typically evidenced via training. | I8: Maturity Scale (0-5) | K8: =IF(J8="","",IF(J8=0,"Band 0",IF(J8<=2,"Band 1-2","Band 3-5"))) | L8: =IF(K8="","Enter a score in column J to see a tailored recommendation.",IFERROR(INDEX('Recommendation Library'!$C:$C,MATCH($A8&"|"&K8,'Recommendation Library'!$D:$D,0)),"Recommendation not found - check the Recommendation Library tab.")) -> Enter a score in column J to see a tailored recommendation.
A9: Q08 | B9: 1. Program Foundation (Policy, Roles, Competence, Awareness) | C9: 8 | D9: Is there an identification process to find out the requirements for each program role? | E9: S3.1.2 Competence (supporting) | F9: Mandatory (shall) | G9: 0.06 | H9: Overlaps with VM 3.1.2.2 (determining necessary competence per role) rather than being a distinct verification material, so weighted lower than the primary competence questions. | I9: Maturity Scale (0-5) | K9: =IF(J9="","",IF(J9=0,"Band 0",IF(J9<=2,"Band 1-2","Band 3-5"))) | L9: =IF(K9="","Enter a score in column J to see a tailored recommendation.",IFERROR(INDEX('Recommendation Library'!$C:$C,MATCH($A9&"|"&K9,'Recommendation Library'!$D:$D,0)),"Recommendation not found - check the Recommendation Library tab.")) -> Enter a score in column J to see a tailored recommendation.
A10: Q09 | B10: 1. Program Foundation (Policy, Roles, Competence, Awareness) | C10: 9 | D10: Is there documentation outlining the compliance requirements and obligations the organization must follow based on domain, customer contracts, service providers, or other relevant factors? | E10: S3.1.5 License Obligations (extension) | F10: Contextual / supporting | G10: 0.05 | H10: Useful context feeding license-obligation reviews (domain- and contract-driven obligations), but not itself a distinct ISO 5230 verification material - supporting detail for S3.1.5. | I10: Maturity Scale (0-5) | K10: =IF(J10="","",IF(J10=0,"Band 0",IF(J10<=2,"Band 1-2","Band 3-5"))) | L10: =IF(K10="","Enter a score in column J to see a tailored recommendation.",IFERROR(INDEX('Recommendation Library'!$C:$C,MATCH($A10&"|"&K10,'Recommendation Library'!$D:$D,0)),"Recommendation not found - check the Recommendation Library tab.")) -> Enter a score in column J to see a tailored recommendation.
A11: Subtotal - 1. Program Foundation (Policy, Roles, Competence, Awareness) | G11: =SUM(G2:G10) -> 1
A12: Q10 | B12: 2. Program Resourcing & External Access | C12: 1 | D12: Is there a documented procedure for assigning internal responsibilities for open source compliance? | E12: S3.2.2 Effectively Resourced (VM 3.2.2.4) | F12: Mandatory (shall) | G12: 0.2 | H12: Directly matches the verification material requiring a documented procedure assigning internal compliance responsibilities - core to making the program actionable, not just defined on paper. | I12: Maturity Scale (0-5) | K12: =IF(J12="","",IF(J12=0,"Band 0",IF(J12<=2,"Band 1-2","Band 3-5"))) | L12: =IF(K12="","Enter a score in column J to see a tailored recommendation.",IFERROR(INDEX('Recommendation Library'!$C:$C,MATCH($A12&"|"&K12,'Recommendation Library'!$D:$D,0)),"Recommendation not found - check the Recommendation Library tab.")) -> Enter a score in column J to see a tailored recommendation.
A13: Q11 | B13: 2. Program Resourcing & External Access | C13: 2 | D13: Is there a documented procedure for handling the review and remediation of Open Source non-compliant cases? | E13: S3.2.2 Effectively Resourced (VM 3.2.2.5) | F13: Mandatory (shall) | G13: 0.2 | H13: Directly matches the verification material for a non-compliance remediation procedure - a required resolution path for license issues, equally central to S3.2. | I13: Maturity Scale (0-5) | K13: =IF(J13="","",IF(J13=0,"Band 0",IF(J13<=2,"Band 1-2","Band 3-5"))) | L13: =IF(K13="","Enter a score in column J to see a tailored recommendation.",IFERROR(INDEX('Recommendation Library'!$C:$C,MATCH($A13&"|"&K13,'Recommendation Library'!$D:$D,0)),"Recommendation not found - check the Recommendation Library tab.")) -> Enter a score in column J to see a tailored recommendation.
A14: Q12 | B14: 2. Program Resourcing & External Access | C14: 3 | D14: Is there a documented procedure in place for open source compliance inquiries to be received and responded to? | E14: S3.2.1 Access (VM 3.2.1.2) | F14: Mandatory (shall) | G14: 0.17 | H14: Matches the internal-side Access requirement: an internal procedure for responding to third-party compliance inquiries once received. | I14: Maturity Scale (0-5) | K14: =IF(J14="","",IF(J14=0,"Band 0",IF(J14<=2,"Band 1-2","Band 3-5"))) | L14: =IF(K14="","Enter a score in column J to see a tailored recommendation.",IFERROR(INDEX('Recommendation Library'!$C:$C,MATCH($A14&"|"&K14,'Recommendation Library'!$D:$D,0)),"Recommendation not found - check the Recommendation Library tab.")) -> Enter a score in column J to see a tailored recommendation.
A15: Q13 | B15: 2. Program Resourcing & External Access | C15: 4 | D15: Has responsibility for receiving external open source compliance inquiries been assigned to specific individual(s)? | E15: S3.2.1 Access (supporting) | F15: Mandatory (shall) | G15: 0.15 | H15: Operational precondition for S3.2.1 - inquiries can't be handled unless a named owner exists to receive them. | I15: Maturity Scale (0-5) | K15: =IF(J15="","",IF(J15=0,"Band 0",IF(J15<=2,"Band 1-2","Band 3-5"))) | L15: =IF(K15="","Enter a score in column J to see a tailored recommendation.",IFERROR(INDEX('Recommendation Library'!$C:$C,MATCH($A15&"|"&K15,'Recommendation Library'!$D:$D,0)),"Recommendation not found - check the Recommendation Library tab.")) -> Enter a score in column J to see a tailored recommendation.
A16: Q14 | B16: 2. Program Resourcing & External Access | C16: 5 | D16: Is the external open source compliance contact publicly identified, for example through an email address or contact details or the Linux Foundation Open Compliance Directory? | E16: S3.2.1 Access (VM 3.2.1.1) | F16: Mandatory (shall) | G16: 0.15 | H16: Matches the public-facing Access verification material - a publicly visible way for third parties to raise a compliance inquiry (e.g., published email or Open Compliance Directory listing). | I16: Yes / No | K16: =IF(J16="","",J16) | L16: =IF(K16="","Enter a score in column J to see a tailored recommendation.",IFERROR(INDEX('Recommendation Library'!$C:$C,MATCH($A16&"|"&K16,'Recommendation Library'!$D:$D,0)),"Recommendation not found - check the Recommendation Library tab.")) -> Enter a score in column J to see a tailored recommendation.
A17: Q15 | B17: 2. Program Resourcing & External Access | C17: 6 | D17: Have the persons, groups, or functions supporting the program roles been documented? | E17: S3.2.2 Effectively Resourced (VM 3.2.2.1) | F17: Mandatory (shall) | G17: 0.13 | H17: Matches the resourcing verification material naming persons/groups/functions in each program role, but overlaps substantially with the roles-and-responsibilities question already scored under Program Foundation, so weighted lowest here. | I17: Maturity Scale (0-5) | K17: =IF(J17="","",IF(J17=0,"Band 0",IF(J17<=2,"Band 1-2","Band 3-5"))) | L17: =IF(K17="","Enter a score in column J to see a tailored recommendation.",IFERROR(INDEX('Recommendation Library'!$C:$C,MATCH($A17&"|"&K17,'Recommendation Library'!$D:$D,0)),"Recommendation not found - check the Recommendation Library tab.")) -> Enter a score in column J to see a tailored recommendation.
A18: Subtotal - 2. Program Resourcing & External Access | G18: =SUM(G12:G17) -> 1
A19: Q16 | B19: 3. Bill of Materials & Content Review | C19: 1 | D19: Is there a documented procedure for identifying, tracking, and archiving information about the open source components in the software that is distributed? | E19: S3.3.1 Bill of Materials (VM 3.3.1.1) | F19: Mandatory (shall) | G19: 0.28 | H19: This is the core Bill of Materials requirement - the documented procedure to identify, track, review, approve and archive OSS component information. The single most important item in this topic. | I19: Maturity Scale (0-5) | K19: =IF(J19="","",IF(J19=0,"Band 0",IF(J19<=2,"Band 1-2","Band 3-5"))) | L19: =IF(K19="","Enter a score in column J to see a tailored recommendation.",IFERROR(INDEX('Recommendation Library'!$C:$C,MATCH($A19&"|"&K19,'Recommendation Library'!$D:$D,0)),"Recommendation not found - check the Recommendation Library tab.")) -> Enter a score in column J to see a tailored recommendation.
A20: Q17 | B20: 3. Bill of Materials & Content Review | C20: 2 | D20: Is open source component inventory for the distributed software available, demonstrating that the documented procedure was properly followed? | E20: S3.3.1 Bill of Materials (VM 3.3.1.2) | F20: Mandatory (shall) | G20: 0.24 | H20: Matches the second BOM verification material - actual component records proving the procedure was followed, not just that it exists on paper. | I20: Maturity Scale (0-5) | K20: =IF(J20="","",IF(J20=0,"Band 0",IF(J20<=2,"Band 1-2","Band 3-5"))) | L20: =IF(K20="","Enter a score in column J to see a tailored recommendation.",IFERROR(INDEX('Recommendation Library'!$C:$C,MATCH($A20&"|"&K20,'Recommendation Library'!$D:$D,0)),"Recommendation not found - check the Recommendation Library tab.")) -> Enter a score in column J to see a tailored recommendation.
A21: Q18 | B21: 3. Bill of Materials & Content Review | C21: 3 | D21: Is there a system in place for verifying the Software Bill of Materials (SBOM) for the software products created and distributed by the organization? | E21: S3.3.1 Bill of Materials (verification emphasis) | F21: Mandatory (shall) | G21: 0.2 | H21: Reinforces S3.3.1 with an emphasis on verification/accuracy of the BOM for outbound (distributed) software, implicit in the standard's 'reviewing and approving' component records language. | I21: Maturity Scale (0-5) | K21: =IF(J21="","",IF(J21=0,"Band 0",IF(J21<=2,"Band 1-2","Band 3-5"))) | L21: =IF(K21="","Enter a score in column J to see a tailored recommendation.",IFERROR(INDEX('Recommendation Library'!$C:$C,MATCH($A21&"|"&K21,'Recommendation Library'!$D:$D,0)),"Recommendation not found - check the Recommendation Library tab.")) -> Enter a score in column J to see a tailored recommendation.
A22: Q19 | B22: 3. Bill of Materials & Content Review | C22: 4 | D22: Does the organization have a process to obtain SBOMs for procured software components and dependencies, including requirements from third-party vendors to ensure license compliance? | E22: Adjacent to S3.3.1 (inbound/procurement BOM) | F22: Supporting practice (not an explicit ISO 5230 requirement) | G22: 0.16 | H22: ISO 5230's BOM requirement is scoped to the supplied (outbound) software, not inbound procurement. This is good practice feeding S3.1.5 and S3.3.1 but is not itself a cited verification material, so weighted as supporting rather than core. | I22: Maturity Scale (0-5) | K22: =IF(J22="","",IF(J22=0,"Band 0",IF(J22<=2,"Band 1-2","Band 3-5"))) | L22: =IF(K22="","Enter a score in column J to see a tailored recommendation.",IFERROR(INDEX('Recommendation Library'!$C:$C,MATCH($A22&"|"&K22,'Recommendation Library'!$D:$D,0)),"Recommendation not found - check the Recommendation Library tab.")) -> Enter a score in column J to see a tailored recommendation.
A23: Q20 | B23: 3. Bill of Materials & Content Review | C23: 5 | D23: Is there a system in place for conducting Software Composition Analysis (SCA) for both the software products created and those used by the organization? | E23: Adjacent to S3.3.1/S3.3.2 (tooling) | F23: Supporting practice (not an explicit ISO 5230 requirement) | G23: 0.12 | H23: SCA is a common tool used to satisfy the BOM and license-obligation requirements but is not named or mandated by the standard itself, so it is the lowest-weighted item in this topic. | I23: Maturity Scale (0-5) | K23: =IF(J23="","",IF(J23=0,"Band 0",IF(J23<=2,"Band 1-2","Band 3-5"))) | L23: =IF(K23="","Enter a score in column J to see a tailored recommendation.",IFERROR(INDEX('Recommendation Library'!$C:$C,MATCH($A23&"|"&K23,'Recommendation Library'!$D:$D,0)),"Recommendation not found - check the Recommendation Library tab.")) -> Enter a score in column J to see a tailored recommendation.
A24: Subtotal - 3. Bill of Materials & Content Review | G24: =SUM(G19:G23) -> 1
A25: Q21 | B25: 4. Compliance Artifact Creation & Delivery | C25: 1 | D25: Is there a documented procedure in place describing the process for ensuring that compliance artifacts are distributed along with the distributed software as required by the identified licenses? | E25: S3.4.1 Compliance Artifacts (VM 3.4.1.1) | F25: Mandatory (shall) | G25: 0.4 | H25: The primary Compliance Artifacts requirement - the documented process for preparing and delivering artifacts (notices, source, license copies) with the software as licenses require. | I25: Maturity Scale (0-5) | K25: =IF(J25="","",IF(J25=0,"Band 0",IF(J25<=2,"Band 1-2","Band 3-5"))) | L25: =IF(K25="","Enter a score in column J to see a tailored recommendation.",IFERROR(INDEX('Recommendation Library'!$C:$C,MATCH($A25&"|"&K25,'Recommendation Library'!$D:$D,0)),"Recommendation not found - check the Recommendation Library tab.")) -> Enter a score in column J to see a tailored recommendation.
A26: Q22 | B26: 4. Compliance Artifact Creation & Delivery | C26: 2 | D26: Is there a documented procedure in place for archiving copies of compliance artifacts for the distributed software? | E26: S3.4.1 Compliance Artifacts (VM 3.4.1.2) | F26: Mandatory (shall) | G26: 0.35 | H26: Matches the archiving half of VM 3.4.1.2 - the documented procedure for retaining compliance artifact copies for the required period. | I26: Maturity Scale (0-5) | K26: =IF(J26="","",IF(J26=0,"Band 0",IF(J26<=2,"Band 1-2","Band 3-5"))) | L26: =IF(K26="","Enter a score in column J to see a tailored recommendation.",IFERROR(INDEX('Recommendation Library'!$C:$C,MATCH($A26&"|"&K26,'Recommendation Library'!$D:$D,0)),"Recommendation not found - check the Recommendation Library tab.")) -> Enter a score in column J to see a tailored recommendation.
A27: Q23 | B27: 4. Compliance Artifact Creation & Delivery | C27: 3 | D27: Are the compliance artifacts archived for at least as long as the distributed software is offered, and as required by the identified licenses? | E27: S3.4.1 Compliance Artifacts (VM 3.4.1.2, duration detail) | F27: Mandatory (shall) | G27: 0.25 | H27: Tests the retention-duration detail within VM 3.4.1.2 rather than the existence of the archiving procedure itself, so scored as a supporting check on the question above. | I27: Maturity Scale (0-5) | K27: =IF(J27="","",IF(J27=0,"Band 0",IF(J27<=2,"Band 1-2","Band 3-5"))) | L27: =IF(K27="","Enter a score in column J to see a tailored recommendation.",IFERROR(INDEX('Recommendation Library'!$C:$C,MATCH($A27&"|"&K27,'Recommendation Library'!$D:$D,0)),"Recommendation not found - check the Recommendation Library tab.")) -> Enter a score in column J to see a tailored recommendation.
A28: Subtotal - 4. Compliance Artifact Creation & Delivery | G28: =SUM(G25:G27) -> 1
A29: Q24 | B29: 5. Open Source Community Contributions | C29: 1 | D29: Is there any open source contribution? | E29: S3.5.1 Contributions (applicability gate) | F29: Gate / Conditional trigger | G29: 0.55 | H29: Marked as the Gate Question in the source file. Per the standard, S3.5.1 only applies 'if an organization considers contributions' - this single Yes/No answer determines whether the entire clause, and the next question, is in scope at all. | I29: Yes / No (Gate) | K29: =IF(J29="","",J29) | L29: =IF(K29="","Enter a score in column J to see a tailored recommendation.",IFERROR(INDEX('Recommendation Library'!$C:$C,MATCH($A29&"|"&K29,'Recommendation Library'!$D:$D,0)),"Recommendation not found - check the Recommendation Library tab.")) -> Enter a score in column J to see a tailored recommendation.
A30: Q25 | B30: 5. Open Source Community Contributions | C30: 2 | D30: Is there a policy in place for contributing to open source projects on behalf of the organization? | E30: S3.5.1 Contributions (VM 3.5.1.1) | F30: Mandatory only if gate = Yes | G30: 0.45 | H30: Matches VM 3.5.1.1 - a documented open source contribution policy. Weighted just under the gate question because it is entirely conditional on that answer. | I30: Maturity Scale (0-5) | K30: =IF(J30="","",IF(J30=0,"Band 0",IF(J30<=2,"Band 1-2","Band 3-5"))) | L30: =IF(J29="No","Not applicable - the organization reported no open source contributions (gate question answered No). No action needed unless contribution activity begins; revisit at the next conformance review.",IF(K30="","Enter a score in column J to see a tailored recommendation.",IFERROR(INDEX('Recommendation Library'!$C:$C,MATCH($A30&"|"&K30,'Recommendation Library'!$D:$D,0)),"Recommendation not found - check the Recommendation Library tab."))) -> Enter a score in column J to see a tailored recommendation.
A31: Subtotal - 5. Open Source Community Contributions | G31: =SUM(G29:G30) -> 1
A32: Q26 | B32: 6. Conformance & Adherence | C32: 1 | D32: Is there documentation verifying that the program complies with all the requirements of ISO 5230:2020? | E32: S3.6.1 Conformance (VM 3.6.1.1) | F32: Mandatory (shall) | G32: 0.55 | H32: The ultimate roll-up requirement - an affirming document that ALL requirements of the standard (not a subset) are satisfied. It depends on every other topic being in place, hence the higher weight of the two conformance questions. | I32: Maturity Scale (0-5) | K32: =IF(J32="","",IF(J32=0,"Band 0",IF(J32<=2,"Band 1-2","Band 3-5"))) | L32: =IF(K32="","Enter a score in column J to see a tailored recommendation.",IFERROR(INDEX('Recommendation Library'!$C:$C,MATCH($A32&"|"&K32,'Recommendation Library'!$D:$D,0)),"Recommendation not found - check the Recommendation Library tab.")) -> Enter a score in column J to see a tailored recommendation.
A33: Q27 | B33: 6. Conformance & Adherence | C33: 2 | D33: Is there a documented procedure confirming that the program's conformance was reviewed within the last 18 months? | E33: S3.6.2 Duration (VM 3.6.2.1) | F33: Mandatory (shall) | G33: 0.45 | H33: Matches the Duration requirement - conformance is only valid for 18 months and must be re-affirmed, preventing the program from going stale. | I33: Maturity Scale (0-5) | K33: =IF(J33="","",IF(J33=0,"Band 0",IF(J33<=2,"Band 1-2","Band 3-5"))) | L33: =IF(K33="","Enter a score in column J to see a tailored recommendation.",IFERROR(INDEX('Recommendation Library'!$C:$C,MATCH($A33&"|"&K33,'Recommendation Library'!$D:$D,0)),"Recommendation not found - check the Recommendation Library tab.")) -> Enter a score in column J to see a tailored recommendation.
A34: Subtotal - 6. Conformance & Adherence | G34: =SUM(G32:G33) -> 1

Sheet Division Recommendations
A1: # | B1: Division / Topic | C1: ISO 5230:2020 Clause | D1: Strategic Recommendation
A2: 1 | B2: 1. Program Foundation (Policy, Roles, Competence, Awareness) | C2: ISO 5230:2020 S3.1 | D2: This division is the base layer the rest of the program depends on - sequence policy and role definition ahead of everything else, since a mature BOM or artifact-delivery process still fails an audit if there's no named owner or written policy behind it. Within this division, prioritize Policy and Roles/Responsibilities first: Awareness/Training and License Obligations naturally follow once those exist, but training people on a policy that doesn't exist, or assigning license-review responsibility to an undefined role, isn't achievable. Once Program Foundation controls reach at least Band 1-2 across the board, shift investment to Program Resourcing, since roles without staffing and funding remain theoretical.
A3: 2 | B3: 2. Program Resourcing & External Access | C3: ISO 5230:2020 S3.2 | D3: Where Program Foundation defines the program on paper, this division makes it operate day to day. Internal responsibility assignment and non-compliance remediation are the two highest-weighted controls here because they determine whether the program can actually respond when something goes wrong, not just when everything goes right - prioritize these over the external-access controls if resourcing is tight. The external-access controls (public contact, inquiry handling) are comparatively quick wins, often closed with a single email alias and a documented SLA, and are worth finishing early since they're the parts of the program visible to customers and partners performing due diligence.
A4: 3 | B4: 3. Bill of Materials & Content Review | C4: ISO 5230:2020 S3.3 | D4: This division is the operational engine of the whole standard: nearly every other division either feeds the BOM procedure or consumes its output. Prioritize the identification/tracking procedure and its resulting inventory records - the two highest-weighted items here - before over-investing in verification tooling; a well-populated but unverified BOM is still more useful than a verification system with nothing reliable to verify. Once basic BOM discipline is in place, extend into inbound/vendor SBOM collection and SCA coverage, which push supply-chain visibility beyond what ISO 5230 strictly requires but align with where SBOM and xBOM regulatory guidance is heading.
A5: 4 | B5: 4. Compliance Artifact Creation & Delivery | C5: ISO 5230:2020 S3.4 | D5: This division is where all the upstream work becomes tangible to customers - a mature BOM and license-review process is worth little if the resulting notices and source offers never actually reach the people who received your software. The artifact-distribution procedure carries the heaviest weight here deliberately, since it's the control most directly tied to real license compliance rather than internal process hygiene. Prioritize it over archiving mechanics if resourcing is limited, then close the archiving and retention-duration controls once distribution itself is reliable.
A6: 5 | B6: 5. Open Source Community Contributions | C6: ISO 5230:2020 S3.5 | D6: This division is entirely conditional, and that conditionality should drive how it's resourced. If the gate question is 'No,' don't invest further here beyond periodically re-confirming the answer - effort is better spent on the other five divisions. If the gate is 'Yes,' treat the contribution-policy gap as urgent rather than optional: unmanaged contribution activity creates IP and licensing exposure the moment it happens, not on some future audit timeline.
A7: 6 | B7: 6. Conformance & Adherence | C7: ISO 5230:2020 S3.6 | D7: These two controls are best understood as the output of the other five divisions rather than an independent workstream - don't attempt the ISO 5230 conformance affirmation before Program Foundation through Compliance Artifacts are reasonably mature, since a premature affirmation is itself a compliance risk if it doesn't hold up under scrutiny. Once conformance is first achieved, the 18-month review cycle is the mechanism that keeps the whole program - and this workbook - a living assessment rather than a one-time snapshot, so build it into a recurring calendar process from day one.

Sheet Topic Summary
A1: # | B1: Topic / Key Concept | C1: ISO 5230:2020 Clause | D1: # Questions | E1: Total Weight (should = 1.00) | F1: Concept Description
A2: 1 | B2: 1. Program Foundation (Policy, Roles, Competence, Awareness) | C2: ISO 5230:2020 S3.1 | D2: 9 | E2: ='Question Mapping'!G11 -> 1 | F2: The written open source policy, defined roles/responsibilities, participant competence, awareness/training, program scope, and the process for reviewing license obligations. This is the base layer every other clause depends on.
A3: 2 | B3: 2. Program Resourcing & External Access | C3: ISO 5230:2020 S3.2 | D3: 6 | E3: ='Question Mapping'!G18 -> 1 | F3: Making sure program roles are actually staffed, funded and accountable, that a remediation path exists for non-compliance, and that third parties have a public, working channel to raise compliance inquiries.
A4: 3 | B4: 3. Bill of Materials & Content Review | C4: ISO 5230:2020 S3.3 | D4: 5 | E4: ='Question Mapping'!G24 -> 1 | F4: Identifying, tracking and archiving the open source components (and their licenses) that make up distributed software, plus handling common license use-cases (binary/source distribution, modification, attribution, etc).
A5: 4 | B5: 4. Compliance Artifact Creation & Delivery | C5: ISO 5230:2020 S3.4 | D5: 3 | E5: ='Question Mapping'!G28 -> 1 | F5: Producing and delivering the compliance artifacts (notices, source offers, license copies, etc.) required by identified licenses, and archiving them for the required retention period.
A6: 5 | B6: 5. Open Source Community Contributions | C6: ISO 5230:2020 S3.5 | D6: 2 | E6: ='Question Mapping'!G31 -> 1 | F6: A conditional clause: only applies if the organization contributes to open source projects. If it does, a contribution policy, procedure and awareness process must exist.
A7: 6 | B7: 6. Conformance & Adherence | C7: ISO 5230:2020 S3.6 | D7: 2 | E7: ='Question Mapping'!G34 -> 1 | F7: The formal affirmation that the program meets every requirement in the standard, and the 18-month cycle for re-confirming that conformance.
B8: TOTAL | D8: =SUM(D2:D7) -> 27 | E8: =SUM(E2:E7)/6 -> 1
B10: Note: each topic's weights are normalized to sum to 1.00 independently, reflecting relative priority WITHIN that topic (not across topics). Topic 5 (Contributions) is fully conditional on its gate question.

Sheet Recommendation Library
A1: Question ID | B1: Band / Answer | C1: Recommendation Text | D1: Lookup Key (hidden helper)
A2: Q01 | B2: Band 0 | C2: This is a foundational gap worth closing first: draft a simple RACI identifying who owns policy authorship, component review and approval, license flagging, and remediation sign-off, and get it approved by a program sponsor. Every other control in the program lacks an accountable owner until this exists. | D2: =A2&"|"&B2 -> Q01|Band 0
A3: Q01 | B3: Band 1-2 | C3: Roles are defined but likely not yet embedded in day-to-day operations. Fold the RACI into each role holder's job description or objectives, and publish it somewhere program participants can actually find it (wiki, onboarding pack) so it survives personnel turnover. | D3: =A3&"|"&B3 -> Q01|Band 1-2
A4: Q01 | B4: Band 3-5 | C4: Roles and responsibilities are defined, documented and embedded. Add a periodic (e.g., annual) review to re-validate the RACI against org changes such as reorganizations or new product lines, and track role vacancy as a program KPI so gaps surface proactively rather than during an incident. | D4: =A4&"|"&B4 -> Q01|Band 3-5
A5: Q02 | B5: Band 0 | C5: No competency requirements exist per role yet. For each role in the RACI, write a short competency profile - for example, the SBOM reviewer should be able to read SPDX/CycloneDX output and interpret common license families. This becomes the basis for hiring, training and gap assessment. | D5: =A5&"|"&B5 -> Q02|Band 0
A6: Q02 | B6: Band 1-2 | C6: Competencies are defined for some or all roles but not yet formally tied to the program. Map each profile explicitly against the tasks that role performs in your actual workflow, and share it with people managers so it's used at hiring and review time rather than filed away. | D6: =A6&"|"&B6 -> Q02|Band 1-2
A7: Q02 | B7: Band 3-5 | C7: Competency requirements are defined and aligned. Introduce an annual self-assessment or skills matrix scored against these competencies, and use the aggregate result to prioritize training investment rather than treating competency definition as a one-time exercise. | D7: =A7&"|"&B7 -> Q02|Band 3-5
A8: Q03 | B8: Band 0 | C8: No evidence is currently kept of individual competence. Start a simple tracker capturing, per program participant, which OSS-compliance training they've completed and any relevant certifications (e.g., Linux Foundation LFC191/193/194) - this is the minimum evidence an auditor will ask for. | D8: =A8&"|"&B8 -> Q03|Band 0
A9: Q03 | B9: Band 1-2 | C9: Some documentation exists but is likely partial or inconsistently maintained. Consolidate it into a single system of record and assign an owner responsible for keeping it current whenever someone joins, changes role, or completes training. | D9: =A9&"|"&B9 -> Q03|Band 1-2
A10: Q03 | B10: Band 3-5 | C10: Competence evidence is documented and current. Tie the record to your role-competency profiles so gaps between required and held competence are visible at a glance, and feed that gap view into training budget planning. | D10: =A10&"|"&B10 -> Q03|Band 3-5
A11: Q04 | B11: Band 0 | C11: No written open source policy exists - this is the single highest-priority gap in the whole assessment. Draft a concise policy covering scope, permitted/prohibited license use, distribution rules and escalation paths, get sign-off from Legal and a business sponsor, and publish it before investing further downstream, since almost every other control assumes this policy already exists. | D11: =A11&"|"&B11 -> Q04|Band 0
A12: Q04 | B12: Band 1-2 | C12: A policy exists but the procedure for employees to actually follow it may be undocumented. Convert it into a short, practical 'how do I comply' guide rather than leaving it as a static legal document, and make it discoverable from wherever developers already work. | D12: =A12&"|"&B12 -> Q04|Band 1-2
A13: Q04 | B13: Band 3-5 | C13: A living policy and procedure exist. Version-control the policy, log the review date and owner within the document itself, and route it through a formal annual (or trigger-based) revision cycle so it doesn't quietly go stale. | D13: =A13&"|"&B13 -> Q04|Band 3-5
... A80: Q27 | B80: Band 3-5 | C80: The 18-month review cycle is institutionalized. Use each cycle to trend maturity scores over time so you can demonstrate continuous improvement, not just repeated pass/fail conformance, to stakeholders. | D80: =A80&"|"&B80 -> Q27|Band 3-5

Sheet ISO 5230 Clause Reference
A1: Clause | B1: Title | C1: What it requires (paraphrased) | D1: # Verification Materials | E1: Mandatory?
A2: S3.1.1 | B2: Policy | C2: A written, internally-communicated open source policy must exist. | D2: 2 | E2: Yes
A3: S3.1.2 | B3: Competence | C3: Roles/responsibilities defined; required competence identified per role; competence assessed and evidenced. | D3: 3 | E3: Yes
A4: S3.1.3 | B4: Awareness | C4: Participants must be made aware of the policy, objectives, their role, and consequences of non-conformance. | D4: 1 | E4: Yes
A5: S3.1.4 | B5: Program scope | C5: A written statement declares the scope and limits of the program (product line, department, or whole org). | D5: 1 | E5: Yes
A6: S3.1.5 | B6: License obligations | C6: A process reviews identified licenses to determine obligations, restrictions and rights. | D6: 1 | E6: Yes
A7: S3.2.1 | B7: Access | C7: A public channel exists for third parties to raise compliance inquiries, plus an internal response procedure. | D7: 2 | E7: Yes
A8: S3.2.2 | B8: Effectively resourced | C8: Program roles are staffed, funded, given legal-expertise access, and have a non-compliance remediation path. | D8: 5 | E8: Yes
A9: S3.3.1 | B9: Bill of materials | C9: A documented procedure identifies, tracks, reviews, approves and archives OSS components in supplied software; records prove it was followed. | D9: 2 | E9: Yes
A10: S3.3.2 | B10: License compliance (use cases) | C10: The program can handle common license use-cases: binary/source distribution, modification, incompatible-license interaction, attribution, etc. | D10: 1 | E10: Yes
A11: S3.4.1 | B11: Compliance artifacts | C11: Artifacts (notices, source, license copies) are prepared/delivered with the software, and archived for the required retention period. | D11: 2 | E11: Yes
A12: S3.5.1 | B12: Contributions | C12: IF the organization contributes to open source, a written, communicated contribution policy and procedure must exist. | D12: 3 | E12: Conditional - only if org contributes
A13: S3.6.1 | B13: Conformance | C13: A document affirms the program satisfies ALL requirements of the standard (not a subset). | D13: 1 | E13: Yes
A14: S3.6.2 | B14: Duration | C14: Conformance is valid for 18 months from validation and must be re-affirmed on that cycle. | D14: 1 | E14: Yes
A16: Source: ISO/IEC 5230:2020 'Information technology - OpenChain Specification' (13 core requirements, S3.1-S3.6). Paraphrased for internal reference; not a reproduction of the standard's text.
